simple_crawler.py
simple_crawler-1.2.dist-info/METADATA
simple_crawler-1.2.dist-info/WHEEL
simple_crawler-1.2.dist-info/top_level.txt
simple_crawler-1.2.dist-info/RECORD
