Metadata-Version: 2.1
Name: simple-crawler
Version: 1.2
Summary: my simple crawler
Home-page: https://github.com/weaming/simple-crawler
Author: weaming
Author-email: garden.yuen@gmail.com
License: UNKNOWN
Project-URL: Source, https://github.com/weaming/simple-crawler
Project-URL: Bug Reports, https://github.com/weaming/simple-crawler
Keywords: crawler
Platform: UNKNOWN
Requires-Dist: beautifulsoup4
Requires-Dist: requests
